plover_retro_quotes/__init__.py
plover_retro_quotes-0.0.2.dist-info/METADATA
plover_retro_quotes-0.0.2.dist-info/RECORD
plover_retro_quotes-0.0.2.dist-info/WHEEL
plover_retro_quotes-0.0.2.dist-info/entry_points.txt
plover_retro_quotes-0.0.2.dist-info/top_level.txt
plover_retro_quotes-0.0.2.dist-info/zip-safe
